tikzplot/__init__.py
tikzplot/plotable.py
tikzplot/plotline.py
tikzplot/plotscatter.py
tikzplot/plotter.py
tikzplot-0.0.2.dist-info/LICENSE
tikzplot-0.0.2.dist-info/METADATA
tikzplot-0.0.2.dist-info/WHEEL
tikzplot-0.0.2.dist-info/top_level.txt
tikzplot-0.0.2.dist-info/RECORD
